<Page 
  xmlns="http://schemas.nativescript.org/tns.xsd" 
  navigatingTo="onNavigatingTo">
  <ActionBar>
    <GridLayout columns="50, *">
        <Label class="action-bar-title" text="Material Symbols" colSpan="2"/>
        <Label class="fas" text="&#xf053;" tap="onBackTap"/>
    </GridLayout>
  </ActionBar>

  <ScrollView>   
    <StackLayout class="p-5">
      <!-- Contoh penerapan pada komponen Label -->
      <Label text="&#xec45;" class="ms-o" />

      <Label textWrap="true">
        <FormattedString>
          <Span text="&#xec45;" class="ms-o" />
          <Span text="Half Star" />
        </FormattedString>
      </Label>

      <!-- Contoh penerapan pada komponen Button -->
      <Button text="&#xec45;" class="ms-o" />

      <Button textWrap="true">
        <FormattedString>
          <Span text="&#xec45;" class="ms-o" />
          <Span text="Half Star" />
        </FormattedString>
      </Button>

      <!-- Contoh penerapan pada komponen Image -->
      <!-- Format untuk di komponen Image -->
      <!-- font:// + &#x + unicode -->
      <Image src="font://&#xec45;" class="ms-o" width="30" height="30" />
    </StackLayout>
  </ScrollView>
</Page>